{
  "1001": {
    "ID": 1001,
    "Name": "生命药剂",
    "ItemType": "消耗品",
    "Quality": "普通",
    "Description": "使用可以恢复少量生命值",
    "Capicity": 999,
    "BuyPrice": 100,
    "SellPrice": 50,
    "Icon": "Sprites/Items/hp",
    "Model": "Items/Bottle_Health",
    "Speed": 0,
    "HPMax": 0,
    "MPMax": 0,
    "AD": 0,
    "AP": 0,
    "DEF": 0,
    "MDEF": 0,
    "CRI": 0,
    "CRD": 0,
    "HitRate": 0,
    "DodgeRate": 0,
    "HpRegen": 0,
    "HpSteal": 0,
    "STR": 0,
    "INT": 0,
    "AGI": 0
  },
  "1002": {
    "ID": 1002,
    "Name": "魔法药剂",
    "ItemType": "消耗品",
    "Quality": "普通",
    "Description": "使用可以恢复少量法力值",
    "Capicity": 999,
    "BuyPrice": 100,
    "SellPrice": 50,
    "Icon": "Sprites/Items/mp",
    "Model": "Items/Bottle_Mana",
    "Speed": 0,
    "HPMax": 0,
    "MPMax": 0,
    "AD": 0,
    "AP": 0,
    "DEF": 0,
    "MDEF": 0,
    "CRI": 0,
    "CRD": 0,
    "HitRate": 0,
    "DodgeRate": 0,
    "HpRegen": 0,
    "HpSteal": 0,
    "STR": 0,
    "INT": 0,
    "AGI": 0
  },
  "1003": {
    "ID": 1003,
    "Name": "内测徽章",
    "ItemType": "道具",
    "Quality": "史诗",
    "Description": "属于内测勇士的专属徽章",
    "Capicity": 1,
    "BuyPrice": 100,
    "SellPrice": 50,
    "Icon": "Icons/stoune_icon",
    "Model": "Items/Box",
    "Speed": 0,
    "HPMax": 0,
    "MPMax": 0,
    "AD": 0,
    "AP": 0,
    "DEF": 0,
    "MDEF": 0,
    "CRI": 0,
    "CRD": 0,
    "HitRate": 0,
    "DodgeRate": 0,
    "HpRegen": 0,
    "HpSteal": 0,
    "STR": 0,
    "INT": 0,
    "AGI": 0
  },
  "1004": {
    "ID": 1004,
    "Name": "升级卷轴",
    "ItemType": "消耗品",
    "Quality": "传说",
    "Description": "使用可以让等级+1",
    "Capicity": 999,
    "BuyPrice": 100,
    "SellPrice": 50,
    "Icon": "Sprites/Items/scroll",
    "Model": "Items/Box",
    "Speed": 0,
    "HPMax": 0,
    "MPMax": 0,
    "AD": 0,
    "AP": 0,
    "DEF": 0,
    "MDEF": 0,
    "CRI": 0,
    "CRD": 0,
    "HitRate": 0,
    "DodgeRate": 0,
    "HpRegen": 0,
    "HpSteal": 0,
    "STR": 0,
    "INT": 0,
    "AGI": 0
  },
  "1005": {
    "ID": 1005,
    "Name": "龙鸣战靴",
    "ItemType": "装备",
    "Quality": "稀有",
    "Description": "朝辞白帝彩云间,千里江陵一日还",
    "Capicity": 1,
    "BuyPrice": 100,
    "SellPrice": 50,
    "Icon": "Sprites/Items/boots",
    "Model": "Items/Box",
    "Speed": 4000,
    "HPMax": 0,
    "MPMax": 0,
    "AD": 0,
    "AP": 0,
    "DEF": 0,
    "MDEF": 0,
    "CRI": 0,
    "CRD": 0,
    "HitRate": 0,
    "DodgeRate": 0,
    "HpRegen": 0,
    "HpSteal": 0,
    "STR": 0,
    "INT": 0,
    "AGI": 0
  },
  "1006": {
    "ID": 1006,
    "Name": "龙鸣战甲",
    "ItemType": "装备",
    "Quality": "稀有",
    "Description": "黄沙百战穿金甲,不破楼兰终不还",
    "Capicity": 1,
    "BuyPrice": 100,
    "SellPrice": 50,
    "Icon": "Sprites/Items/armor",
    "Model": "Items/Box",
    "Speed": 0,
    "HPMax": 600,
    "MPMax": 0,
    "AD": 0,
    "AP": 0,
    "DEF": 150,
    "MDEF": 0,
    "CRI": 0,
    "CRD": 0,
    "HitRate": 0,
    "DodgeRate": 0,
    "HpRegen": 0,
    "HpSteal": 0,
    "STR": 0,
    "INT": 0,
    "AGI": 0
  }
}