{
  "1": {
    "ID": 1,
    "MapId": 1,
    "Pos": "[-53,-4,42]",
    "Dir": "[0,0,0]",
    "UnitID": 1005,
    "Level": 6,
    "Period": 20,
    "killRewardList": "",
    "WalkRange": 3,
    "ChaseRange": 3,
    "AttackRange": 1
  },
  "2": {
    "ID": 2,
    "MapId": 1,
    "Pos": "[-36,6,-86]",
    "Dir": "[0,0,0]",
    "UnitID": 1007,
    "Level": 20,
    "Period": 40,
    "killRewardList": "",
    "WalkRange": 3,
    "ChaseRange": 3,
    "AttackRange": 2
  },
  "3": {
    "ID": 3,
    "MapId": 1,
    "Pos": "[-36,6,-86]",
    "Dir": "[0,0,0]",
    "UnitID": 1007,
    "Level": 22,
    "Period": 40,
    "killRewardList": "",
    "WalkRange": 3,
    "ChaseRange": 3,
    "AttackRange": 2
  },
  "4": {
    "ID": 4,
    "MapId": 1,
    "Pos": "[-53,-4,42]",
    "Dir": "[0,0,0]",
    "UnitID": 1006,
    "Level": 9,
    "Period": 30,
    "killRewardList": "",
    "WalkRange": 3,
    "ChaseRange": 3,
    "AttackRange": 1
  },
  "5": {
    "ID": 5,
    "MapId": 1,
    "Pos": "[-53,-4,42]",
    "Dir": "[0,0,0]",
    "UnitID": 1006,
    "Level": 10,
    "Period": 30,
    "killRewardList": "",
    "WalkRange": 3,
    "ChaseRange": 3,
    "AttackRange": 1
  }
}